bridgedbpy.py
bridgedbpy/__init__.py
bridgedbpy/_version.py
bridgedbpy/get_full_name.py
bridgedbpy/get_organism_code.py
bridgedbpy/get_system_code.py
bridgedbpy-0.0.2.dist-info/LICENSE
bridgedbpy-0.0.2.dist-info/METADATA
bridgedbpy-0.0.2.dist-info/WHEEL
bridgedbpy-0.0.2.dist-info/top_level.txt
bridgedbpy-0.0.2.dist-info/RECORD
