Metadata-Version: 2.1
Name: bridgedbpy
Version: 0.0.2
Summary: Code for using BridgeDb identifier mapping framework from within Python
Home-page: https://github.com/kozo2/bridgedbpy
Author: Kozo Nishida
Author-email: kozo.nishida@gmail.com
Maintainer: Kozo Nishida
Maintainer-email: kozo.nishida@gmail.com
License: AGPL-3
Keywords: wikipathways,bioinformatics
Platform: UNKNOWN
Classifier: Intended Audience :: Science/Research
Classifier: Intended Audience :: Developers
Classifier: Programming Language :: Python :: 3
Classifier: License :: OSI Approved :: MIT License
Classifier: Operating System :: OS Independent
Classifier: Topic :: Scientific/Engineering :: Bio-Informatics
Classifier: Topic :: Scientific/Engineering :: Information Analysis
Classifier: Topic :: Scientific/Engineering :: Mathematics
Requires-Python: >=3.7
License-File: LICENSE
Requires-Dist: requests
Requires-Dist: pandas
